[
  {
    "id": "fd2cb06f-5c47-4d4f-8da3-c1cf6cbcf6cf",
    "userId": "64dc38b1-ddbe-4025-a15a-70080c1f21a0",
    "phone": "99999999999",
    "address": {
      "cep": "5210032",
      "street": "rua exemplo tal",
      "number": "12",
      "neighborhood": "bairro exemplo",
      "city": "Recife",
      "state": "PB"
    }
  },
  {
    "id": "9aa42020-525b-4180-8497-513fc52452c5",
    "userId": "addd2cde-dd1f-4a52-960e-8cf0b0ad4103",
    "phone": "99999999999",
    "address": {
      "cep": "",
      "street": "",
      "number": "",
      "city": "Recife",
      "state": "PE"
    }
  },
  {
    "id": "f704317a-d106-40f3-9411-0ed0d005fdd5",
    "userId": "bfc21db5-42bd-4893-aac8-720b19afba92",
    "phone": "",
    "address": {
      "cep": "",
      "street": "",
      "number": "",
      "city": "",
      "state": ""
    }
  }
]